StarData/Error.py
StarData/StarData.py
StarData/__init__.py
StarData-1.0.0.dist-info/LICENSE
StarData-1.0.0.dist-info/METADATA
StarData-1.0.0.dist-info/WHEEL
StarData-1.0.0.dist-info/top_level.txt
StarData-1.0.0.dist-info/RECORD
